{
  "basic_blocks": [
    {
      "entry_node_id": 0,
      "function_id": 0,
      "id": 0,
      "label": "label %1"
    },
    {
      "entry_node_id": 4,
      "function_id": 1,
      "id": 1,
      "label": "label %0"
    }
  ],
  "edges": [
    {
      "id": 0,
      "kind": "instruction_sequence",
      "label": null,
      "source_basic_block_id": null,
      "source_function_id": null,
      "source_node_id": 0,
      "successor_index": null,
      "target_basic_block_id": null,
      "target_function_id": null,
      "target_node_id": 1
    },
    {
      "id": 1,
      "kind": "instruction_sequence",
      "label": null,
      "source_basic_block_id": null,
      "source_function_id": null,
      "source_node_id": 1,
      "successor_index": null,
      "target_basic_block_id": null,
      "target_function_id": null,
      "target_node_id": 2
    },
    {
      "id": 2,
      "kind": "instruction_sequence",
      "label": null,
      "source_basic_block_id": null,
      "source_function_id": null,
      "source_node_id": 2,
      "successor_index": null,
      "target_basic_block_id": null,
      "target_function_id": null,
      "target_node_id": 3
    },
    {
      "id": 3,
      "kind": "instruction_sequence",
      "label": null,
      "source_basic_block_id": null,
      "source_function_id": null,
      "source_node_id": 4,
      "successor_index": null,
      "target_basic_block_id": null,
      "target_function_id": null,
      "target_node_id": 5
    },
    {
      "id": 4,
      "kind": "data_flow",
      "label": "%2",
      "source_basic_block_id": null,
      "source_function_id": null,
      "source_node_id": 0,
      "successor_index": null,
      "target_basic_block_id": null,
      "target_function_id": null,
      "target_node_id": 1
    },
    {
      "id": 5,
      "kind": "data_flow",
      "label": "%0",
      "source_basic_block_id": null,
      "source_function_id": null,
      "source_node_id": 6,
      "successor_index": null,
      "target_basic_block_id": null,
      "target_function_id": null,
      "target_node_id": 0
    },
    {
      "id": 6,
      "kind": "data_flow",
      "label": null,
      "source_basic_block_id": null,
      "source_function_id": null,
      "source_node_id": 7,
      "successor_index": null,
      "target_basic_block_id": null,
      "target_function_id": null,
      "target_node_id": 0
    },
    {
      "id": 7,
      "kind": "data_flow",
      "label": "%3",
      "source_basic_block_id": null,
      "source_function_id": null,
      "source_node_id": 1,
      "successor_index": null,
      "target_basic_block_id": null,
      "target_function_id": null,
      "target_node_id": 2
    },
    {
      "id": 8,
      "kind": "data_flow",
      "label": null,
      "source_basic_block_id": null,
      "source_function_id": null,
      "source_node_id": 8,
      "successor_index": null,
      "target_basic_block_id": null,
      "target_function_id": null,
      "target_node_id": 1
    },
    {
      "id": 9,
      "kind": "data_flow",
      "label": null,
      "source_basic_block_id": null,
      "source_function_id": null,
      "source_node_id": 9,
      "successor_index": null,
      "target_basic_block_id": null,
      "target_function_id": null,
      "target_node_id": 1
    },
    {
      "id": 10,
      "kind": "data_flow",
      "label": null,
      "source_basic_block_id": null,
      "source_function_id": null,
      "source_node_id": 10,
      "successor_index": null,
      "target_basic_block_id": null,
      "target_function_id": null,
      "target_node_id": 2
    },
    {
      "id": 11,
      "kind": "data_flow",
      "label": null,
      "source_basic_block_id": null,
      "source_function_id": null,
      "source_node_id": 11,
      "successor_index": null,
      "target_basic_block_id": null,
      "target_function_id": null,
      "target_node_id": 4
    },
    {
      "id": 12,
      "kind": "data_flow",
      "label": null,
      "source_basic_block_id": null,
      "source_function_id": null,
      "source_node_id": 12,
      "successor_index": null,
      "target_basic_block_id": null,
      "target_function_id": null,
      "target_node_id": 4
    },
    {
      "id": 13,
      "kind": "data_flow",
      "label": null,
      "source_basic_block_id": null,
      "source_function_id": null,
      "source_node_id": 13,
      "successor_index": null,
      "target_basic_block_id": null,
      "target_function_id": null,
      "target_node_id": 5
    }
  ],
  "functions": [
    {
      "entry_basic_block_id": 0,
      "entry_node_id": 0,
      "id": 0,
      "name": "func"
    },
    {
      "entry_basic_block_id": 1,
      "entry_node_id": 4,
      "id": 1,
      "name": "main"
    },
    {
      "entry_basic_block_id": null,
      "entry_node_id": null,
      "id": 2,
      "name": "puts"
    }
  ],
  "module_name": "examples/hello/hello.c",
  "nodes": [
    {
      "basic_block_id": 0,
      "consumer_instruction_id": null,
      "function_id": 0,
      "id": 0,
      "kind": "instruction",
      "label": "icmp",
      "opcode_name": "icmp",
      "operand_index": null,
      "operand_kind": null
    },
    {
      "basic_block_id": 0,
      "consumer_instruction_id": null,
      "function_id": 0,
      "id": 1,
      "kind": "instruction",
      "label": "select",
      "opcode_name": "select",
      "operand_index": null,
      "operand_kind": null
    },
    {
      "basic_block_id": 0,
      "consumer_instruction_id": null,
      "function_id": 0,
      "id": 2,
      "kind": "instruction",
      "label": "call",
      "opcode_name": "call",
      "operand_index": null,
      "operand_kind": null
    },
    {
      "basic_block_id": 0,
      "consumer_instruction_id": null,
      "function_id": 0,
      "id": 3,
      "kind": "instruction",
      "label": "ret",
      "opcode_name": "ret",
      "operand_index": null,
      "operand_kind": null
    },
    {
      "basic_block_id": 1,
      "consumer_instruction_id": null,
      "function_id": 1,
      "id": 4,
      "kind": "instruction",
      "label": "call",
      "opcode_name": "call",
      "operand_index": null,
      "operand_kind": null
    },
    {
      "basic_block_id": 1,
      "consumer_instruction_id": null,
      "function_id": 1,
      "id": 5,
      "kind": "instruction",
      "label": "ret",
      "opcode_name": "ret",
      "operand_index": null,
      "operand_kind": null
    },
    {
      "basic_block_id": 0,
      "consumer_instruction_id": 0,
      "function_id": 0,
      "id": 6,
      "kind": "operand",
      "label": "i32 %0",
      "opcode_name": null,
      "operand_index": 0,
      "operand_kind": "argument"
    },
    {
      "basic_block_id": 0,
      "consumer_instruction_id": 0,
      "function_id": 0,
      "id": 7,
      "kind": "operand",
      "label": "i32 0",
      "opcode_name": null,
      "operand_index": 1,
      "operand_kind": "constant"
    },
    {
      "basic_block_id": 0,
      "consumer_instruction_id": 1,
      "function_id": 0,
      "id": 8,
      "kind": "operand",
      "label": "ptr @str",
      "opcode_name": null,
      "operand_index": 1,
      "operand_kind": "global_value"
    },
    {
      "basic_block_id": 0,
      "consumer_instruction_id": 1,
      "function_id": 0,
      "id": 9,
      "kind": "operand",
      "label": "ptr @str.2",
      "opcode_name": null,
      "operand_index": 2,
      "operand_kind": "global_value"
    },
    {
      "basic_block_id": 0,
      "consumer_instruction_id": 2,
      "function_id": 0,
      "id": 10,
      "kind": "operand",
      "label": "ptr @puts",
      "opcode_name": null,
      "operand_index": 1,
      "operand_kind": "function"
    },
    {
      "basic_block_id": 1,
      "consumer_instruction_id": 4,
      "function_id": 1,
      "id": 11,
      "kind": "operand",
      "label": "ptr @str.2",
      "opcode_name": null,
      "operand_index": 0,
      "operand_kind": "global_value"
    },
    {
      "basic_block_id": 1,
      "consumer_instruction_id": 4,
      "function_id": 1,
      "id": 12,
      "kind": "operand",
      "label": "ptr @puts",
      "opcode_name": null,
      "operand_index": 1,
      "operand_kind": "function"
    },
    {
      "basic_block_id": 1,
      "consumer_instruction_id": 5,
      "function_id": 1,
      "id": 13,
      "kind": "operand",
      "label": "i32 0",
      "opcode_name": null,
      "operand_index": 0,
      "operand_kind": "constant"
    }
  ]
}
